topsis_bharat132/package_101703139.py
topsis_bharat-4.0.0.dist-info/LICENSE
topsis_bharat-4.0.0.dist-info/METADATA
topsis_bharat-4.0.0.dist-info/WHEEL
topsis_bharat-4.0.0.dist-info/entry_points.txt
topsis_bharat-4.0.0.dist-info/top_level.txt
topsis_bharat-4.0.0.dist-info/RECORD
