Metadata-Version: 2.1
Name: topsis-bharat
Version: 4.0.0
Summary: A TOPSIS Python package.
Home-page: UNKNOWN
Author: Bharat Chauhan
Author-email: bharatchauhan752000@gmail.com
License: MIT
Platform: UNKNOWN
Classifier: License :: OSI Approved :: MIT License
Classifier: Programming Language :: Python :: 3
Classifier: Programming Language :: Python :: 3.7
Requires-Dist: pandas
